tranzor/__init__.py
tranzor/base_code.py
tranzor/color_code.py
tranzor/compile.py
tranzor/py.typed
tranzor/utils.py
tranzor-0.1.0.dist-info/METADATA
tranzor-0.1.0.dist-info/WHEEL
tranzor-0.1.0.dist-info/licenses/LICENSE
tranzor-0.1.0.dist-info/RECORD
