Metadata-Version: 2.4
Name: tranzor
Version: 0.1.0
Summary: Transversal Clifford logical circuit generator for color code.
Author-email: Yiming Zhang <zhangyiming21@mail.ustc.edu.cn>
License-File: LICENSE
Requires-Python: >=3.10
Requires-Dist: stim>=1.15
